himpunan_team7/__init__.py
himpunan_team7/main.py
himpunan_team7-0.1.0.dist-info/METADATA
himpunan_team7-0.1.0.dist-info/WHEEL
himpunan_team7-0.1.0.dist-info/top_level.txt
himpunan_team7-0.1.0.dist-info/RECORD
