Metadata-Version: 2.1
Name: himpunan-team7
Version: 0.1.0
Summary: A Python package for performing set operations (Himpunan)
Author: Aaron Jevon Benedict Kongdoh, Derick Norlan, Excel Marcello Parinussa
